{
  "schemaVersion": "2.0",
  "repos": [
    {
      "repo": "microsoft-go/infra-images",
      "images": [
        {
          "productVersion": "",
          "platforms": [
            {
              "dockerfile": "src/azurelinux/3.0/amd64/default/Dockerfile",
              "simpleTags": [
                "azurelinux-3.0-amd64-default"
              ],
              "digest": "mcr.microsoft.com/microsoft-go/infra-images@sha256:b7d0562608801386c11e1160d6dc291afceb27d59c0fa89f3c09532d803173c1",
              "baseImageDigest": "mcr.microsoft.com/dotnet/sdk@sha256:546d995e9a1f9bd2777b2359e8294abed2c00a537fd1647901d8b27718579170",
              "osType": "Linux",
              "osVersion": "3.0",
              "architecture": "amd64",
              "created": "2025-10-21T10:22:45.3573106Z",
              "commitUrl": "https://github.com/microsoft/go/blob/a3a120309530ccde050c6e5dc733d092af771cf0/src/azurelinux/3.0/amd64/default/Dockerfile",
              "layers": [
                {
                  "digest": "sha256:534237c6e26529734cdf96a8a73abb18ed0f1d11c800db2adf1e795de1e5b0d7",
                  "size": 153646585
                },
                {
                  "digest": "sha256:52a722ea818348f1f41729a4ce73daec498d3d92cf8ba2049ddecebd7c494383",
                  "size": 17452158
                },
                {
                  "digest": "sha256:d15443561bc78b514780bfb3310911b97681415d24f7d563bbc7283d0c172812",
                  "size": 2662
                },
                {
                  "digest": "sha256:ba8cd8477b56547e5cafec45085d6163d5e6cfd581e74c0a1a0726c7640dd2cc",
                  "size": 176287475
                },
                {
                  "digest": "sha256:0f676b57e10d7f601bd6a94bd10e06408e4ed3f6bc8fae20b6353a64dc06a6b6",
                  "size": 42234263
                },
                {
                  "digest": "sha256:bac7ac0aa62386229864a0236725ad89e39e77b6c4bc34815ba4f45d216eb806",
                  "size": 11312925
                },
                {
                  "digest": "sha256:8b8531396c4679e94799be78afe0e493a553d4db22e37d7d4c2629f065ea63c5",
                  "size": 154
                },
                {
                  "digest": "sha256:0573ec1c16178fe35cec230a18fd2c4f2706b21d97e01dbbcc4214411e6ca638",
                  "size": 34553171
                },
                {
                  "digest": "sha256:f2649d1efd06533c811c50ad85dd2b887158efff9b273860e141d09ac13ea41a",
                  "size": 760751
                },
                {
                  "digest": "sha256:685f7a137bbc3f176b360f7e8c415d8e1d274e9ef1949c8cb1d6a0c110cb04c0",
                  "size": 22880793
                },
                {
                  "digest": "sha256:9ab3635ac74c19c3292626d84c3b56977212321acef5ec9e9c69ffae13c84476",
                  "size": 31722791
                }
              ]
            }
          ]
        },
        {
          "productVersion": "",
          "platforms": [
            {
              "dockerfile": "src/cbl-mariner/2.0/amd64/default/Dockerfile",
              "simpleTags": [
                "cbl-mariner-2.0-amd64-default"
              ],
              "digest": "mcr.microsoft.com/microsoft-go/infra-images@sha256:0a82a97e3d55f382a77591e601d5c5b0e3b98135279f06b3a1df82e762ab27a3",
              "baseImageDigest": "mcr.microsoft.com/cbl-mariner/base/core@sha256:9d888a796a79fcb315f4895e39c38a7913f752347395fd63f1f22464630a92a6",
              "osType": "Linux",
              "osVersion": "2.0",
              "architecture": "amd64",
              "created": "2025-10-21T10:23:56.4689117Z",
              "commitUrl": "https://github.com/microsoft/go/blob/6049f85a39d9ec5a06399ed9e2dfc68d11da74a3/src/cbl-mariner/2.0/amd64/default/Dockerfile",
              "layers": [
                {
                  "digest": "sha256:91b7ab9fec6c5e66a89ad522389fbb631cc869e1829fea0f103febaec7d5256d",
                  "size": 284229402
                },
                {
                  "digest": "sha256:9cc3f1e62d5a8355fe382ce970869032d811b7b9dc90493311831017f508f590",
                  "size": 4466
                },
                {
                  "digest": "sha256:2141b125dc895c7cc333a006b47145db2d62a8f5609530647bccca5133c75a05",
                  "size": 28717388
                }
              ]
            }
          ]
        },
        {
          "productVersion": "",
          "platforms": [
            {
              "dockerfile": "src/cbl-mariner/2.0/arm64/default/Dockerfile",
              "simpleTags": [
                "cbl-mariner-2.0-arm64-default"
              ],
              "digest": "mcr.microsoft.com/microsoft-go/infra-images@sha256:9a5c849b57e01f46a287eb17775b3ee73fce72fdc10f0f045839e8521acce035",
              "baseImageDigest": "mcr.microsoft.com/cbl-mariner/base/core@sha256:9d888a796a79fcb315f4895e39c38a7913f752347395fd63f1f22464630a92a6",
              "osType": "Linux",
              "osVersion": "2.0",
              "architecture": "arm64",
              "created": "2025-10-21T10:14:52.2322892Z",
              "commitUrl": "https://github.com/microsoft/go/blob/6049f85a39d9ec5a06399ed9e2dfc68d11da74a3/src/cbl-mariner/2.0/arm64/default/Dockerfile",
              "layers": [
                {
                  "digest": "sha256:7229c2181aa797bd52b84d01310b3d649a6ed30d226f5004f01bbc91125bc3a9",
                  "size": 272828648
                },
                {
                  "digest": "sha256:9a7dcbb5fd9fb436b87972f1cc5eb3cd554bd2038c32aa413aa639a65276af3f",
                  "size": 4465
                },
                {
                  "digest": "sha256:032ae246be5f28a597c101b9256f69c400194cf50a2d36bbce006b7da27c96e9",
                  "size": 27218995
                }
              ]
            }
          ]
        },
        {
          "productVersion": "",
          "platforms": [
            {
              "dockerfile": "src/ubuntu/22.04/amd64/default/Dockerfile",
              "simpleTags": [
                "ubuntu-22.04-amd64-default"
              ],
              "digest": "mcr.microsoft.com/microsoft-go/infra-images@sha256:198c214508b33b9a8affd4b2f21b9ace8c4516bb35fdd0b16a7074429813a1f6",
              "baseImageDigest": "ubuntu.azurecr.io/ubuntu@sha256:2d50a274db7c4875851bc825c12e0b93732d3f162177c21a7cd73d999134b046",
              "osType": "Linux",
              "osVersion": "22.04",
              "architecture": "amd64",
              "created": "2025-10-21T10:23:40.5306322Z",
              "commitUrl": "https://github.com/microsoft/go/blob/02e866384225c63c84cc127dfac766adb650f484/src/ubuntu/22.04/amd64/default/Dockerfile",
              "layers": [
                {
                  "digest": "sha256:e9d67b36fd4d960f64ff6f1a34ae111941e354f906e0db7590711f9485cbf7f4",
                  "size": 77740843
                },
                {
                  "digest": "sha256:3d023d1e8b8eb80da087850eaed2843ac377bbeffd6604592321e5cf2ce1a6ef",
                  "size": 940
                },
                {
                  "digest": "sha256:1c0ee7dd582ecdc37d5c67af924413cc966156962e4718a346b7e5850d8517c1",
                  "size": 2974510
                },
                {
                  "digest": "sha256:911fd7ad538b126003e4dc67faf605b63121d1a494f0f916701a3203fae2c959",
                  "size": 150115697
                },
                {
                  "digest": "sha256:7e49dc6156b0b532730614d83a65ae5e7ce61e966b0498703d333b4d03505e4f",
                  "size": 29536798
                }
              ]
            }
          ]
        }
      ]
    }
  ]
}
